{
  "project_info": {
    "project_number": "1007225187624",
    "firebase_url": "https://events-f6847.firebaseio.com",
    "project_id": "events-f6847",
    "storage_bucket": "events-f6847.appspot.com"
  },
  "client": [
    {
      "client_info": {
        "mobilesdk_app_id": "1:1007225187624:android:ebced62f45f7b4e3",
        "android_client_info": {
          "package_name": "com.macbitsgoa.events"
        }
      },
      "oauth_client": [
        {
          "client_id": "1007225187624-mr80d7mq30pideg21fk89sna2c4p67go.apps.googleusercontent.com",
          "client_type": 1,
          "android_info": {
            "package_name": "com.macbitsgoa.events",
            "certificate_hash": "506cc66679f84c1e583cb61b04e321c6f3b42b45"
          }
        },
        {
          "client_id": "1007225187624-hfshif3nq20l6t8vn6jdf4f2lek8m7mi.apps.googleusercontent.com",
          "client_type": 1,
          "android_info": {
            "package_name": "com.macbitsgoa.events",
            "certificate_hash": "7a14bf20a66329babeaf07ee0666518ee528ae36"
          }
        },
        {
          "client_id": "1007225187624-12ptaqojg9uh9mni661itrlc437bpq2r.apps.googleusercontent.com",
          "client_type": 1,
          "android_info": {
            "package_name": "com.macbitsgoa.events",
            "certificate_hash": "3b52590e51617c9f05f48c10736ba59054faecba"
          }
        },
        {
          "client_id": "1007225187624-6plsc07ro9vng0rc3lbkpb13m1spoddj.apps.googleusercontent.com",
          "client_type": 1,
          "android_info": {
            "package_name": "com.macbitsgoa.events",
            "certificate_hash": "3b671ed1d2f5f1936948b9d4c3221aae91f6b5b7"
          }
        },
        {
          "client_id": "1007225187624-a5daqiisnmmg570aon56cbq4b9vd2qpq.apps.googleusercontent.com",
          "client_type": 1,
          "android_info": {
            "package_name": "com.macbitsgoa.events",
            "certificate_hash": "1478ae20256d4c951da15e3dadf0092fdee28993"
          }
        },
        {
          "client_id": "1007225187624-k5pue6i8esjd3je00audoh5loer69fr9.apps.googleusercontent.com",
          "client_type": 1,
          "android_info": {
            "package_name": "com.macbitsgoa.events",
            "certificate_hash": "691c9e26f5d642b23fe6899c9a699cd2645fd639"
          }
        },
        {
          "client_id": "1007225187624-gfvc2b74nk8vddqoa95ih0mmk6muksfr.apps.googleusercontent.com",
          "client_type": 1,
          "android_info": {
            "package_name": "com.macbitsgoa.events",
            "certificate_hash": "f3617c88c5c6974f7def83821a5eaf12c7fbd78a"
          }
        },
        {
          "client_id": "1007225187624-ve88c33iuivn0u1ulp8d3ajm8sbh95ai.apps.googleusercontent.com",
          "client_type": 3
        }
      ],
      "api_key": [
        {
          "current_key": "AIzaSyBvvY8ArhPb3FLvWSyCXSXIm2aURp1mAFg"
        }
      ],
      "services": {
        "analytics_service": {
          "status": 1
        },
        "appinvite_service": {
          "status": 2,
          "other_platform_oauth_client": [
            {
              "client_id": "1007225187624-ve88c33iuivn0u1ulp8d3ajm8sbh95ai.apps.googleusercontent.com",
              "client_type": 3
            }
          ]
        },
        "ads_service": {
          "status": 2
        }
      }
    },
    {
      "client_info": {
        "mobilesdk_app_id": "1:1007225187624:android:7dc76ce2b0557359",
        "android_client_info": {
          "package_name": "com.macbitsgoa.events.debug"
        }
      },
      "oauth_client": [
        {
          "client_id": "1007225187624-ucdsmtdbkekn29ablofq8d36kdbpnlb4.apps.googleusercontent.com",
          "client_type": 1,
          "android_info": {
            "package_name": "com.macbitsgoa.events.debug",
            "certificate_hash": "506cc66679f84c1e583cb61b04e321c6f3b42b45"
          }
        },
        {
          "client_id": "1007225187624-g72ag38cvbdsttk5qg2bd0gdoodhtdf5.apps.googleusercontent.com",
          "client_type": 1,
          "android_info": {
            "package_name": "com.macbitsgoa.events.debug",
            "certificate_hash": "691c9e26f5d642b23fe6899c9a699cd2645fd639"
          }
        },
        {
          "client_id": "1007225187624-ve88c33iuivn0u1ulp8d3ajm8sbh95ai.apps.googleusercontent.com",
          "client_type": 3
        }
      ],
      "api_key": [
        {
          "current_key": "AIzaSyBvvY8ArhPb3FLvWSyCXSXIm2aURp1mAFg"
        }
      ],
      "services": {
        "analytics_service": {
          "status": 1
        },
        "appinvite_service": {
          "status": 2,
          "other_platform_oauth_client": [
            {
              "client_id": "1007225187624-ve88c33iuivn0u1ulp8d3ajm8sbh95ai.apps.googleusercontent.com",
              "client_type": 3
            }
          ]
        },
        "ads_service": {
          "status": 2
        }
      }
    }
  ],
  "configuration_version": "1"
}